double_stream_handler/__init__.py
double_stream_handler-1.0.0.dist-info/LICENSE
double_stream_handler-1.0.0.dist-info/WHEEL
double_stream_handler-1.0.0.dist-info/METADATA
double_stream_handler-1.0.0.dist-info/RECORD
