Metadata-Version: 2.1
Name: double-stream-handler
Version: 1.0.0
Summary: A StreamHandler wrapper that outputs messages to different streams based on logLevel
Home-page: https://github.com/NickKaramoff/DoubleStreamHandler/
License: BSD-3-Clause
Keywords: logging,handler,StreamHandler
Author: Nikita Karamov
Author-email: nick@karamoff.dev
Requires-Python: >=3.6,<4.0
Classifier: Development Status :: 5 - Production/Stable
Classifier: Environment :: Console
Classifier: Environment :: Plugins
Classifier: Intended Audience :: Developers
Classifier: Intended Audience :: System Administrators
Classifier: License :: OSI Approved :: BSD License
Classifier: Operating System :: OS Independent
Classifier: Programming Language :: Python :: 3
Classifier: Programming Language :: Python :: 3.6
Classifier: Programming Language :: Python :: 3.7
Classifier: Programming Language :: Python :: 3.8
Classifier: Programming Language :: Python :: 3.9
Classifier: Topic :: Software Development :: Libraries :: Python Modules
Classifier: Topic :: System :: Logging
Project-URL: Bug Tracker, https://github.com/NickKaramoff/DoubleStreamHandler/issues
Project-URL: Repository, https://github.com/NickKaramoff/DoubleStreamHandler/
